<?xml version="1.0" encoding="utf-8"?>
<!DOCTYPE knimeNode PUBLIC "-//UNIKN//DTD KNIME Node 1.0//EN" "http://www.inf.uni-konstanz.de/bioml/research/knime/Node.dtd">
<knimeNode icon="" type="Source">
	<name>Meta Data Input Node</name>
	
	<shortDescription>
		Transfers data tables into the meta workflow
	</shortDescription>
	
	<fullDescription>
		<intro>The Meta Data Input Node transfers data table from the outer workflow
			into the inner workflow without chaning anything.
		</intro>
	</fullDescription>
	
	<ports>
		<dataOut name="Transfered data table" index="0">Datatable from the connected successor outside</dataOut>
	</ports>	
</knimeNode>