{
    "type": "VerticalLayout",
    "elements": [
        {
            "type": "Section",
            "label": "Data",
            "elements": [
                {
                    "type": "Control",
                    "scope": "#/properties/view/properties/displayedColumns",
                    "options": {
                        "format": "columnFilter"
                    }
                },
                {
                    "type": "Control",
                    "scope": "#/properties/view/properties/showRowKeys",
                    "options": {
                        "format": "checkbox"
                    }
                },
                {
                    "type": "Control",
                    "scope": "#/properties/view/properties/showColumnDataType",
                    "options": {
                        "format": "checkbox"
                    }
                },
                {
                    "type": "Control",
                    "scope": "#/properties/view/properties/showRowIndices",
                    "options": {
                        "format": "checkbox"
                    }
                }
            ]
        },
        {
            "type": "Section",
            "label": "View",
            "elements": [
                {
                    "type": "Control",
                    "scope": "#/properties/view/properties/title"
                },
                {
                    "type": "Control",
                    "scope": "#/properties/view/properties/showTitle",
                    "options": {
                        "format": "checkbox"
                    }
                },
                {
                    "type": "Control",
                    "scope": "#/properties/view/properties/enablePagination",
                    "options": {
                        "format": "checkbox"
                    }
                },
                {
                    "type": "Control",
                    "scope": "#/properties/view/properties/pageSize"
                },
                {
                    "type": "Control",
                    "scope": "#/properties/view/properties/compactMode",
                    "options": {
                        "format": "checkbox"
                    }
                }
            ]
        },
        {
            "type": "Section",
            "label": "Interactivity",
            "elements": [
                {
                    "type": "Control",
                    "scope": "#/properties/view/properties/enableGlobalSearch",
                    "options": {
                        "format": "checkbox"
                    }
                },
                {
                    "type": "Control",
                    "scope": "#/properties/view/properties/enableColumnSearch",
                    "options": {
                        "format": "checkbox"
                    }
                },
                {
                    "type": "Control",
                    "scope": "#/properties/view/properties/enableSortingByHeader",
                    "options": {
                        "format": "checkbox"
                    }
                },
                {
                    "type": "Control",
                    "scope": "#/properties/view/properties/publishSelection",
                    "options": {
                        "format": "checkbox"
                    }
                },
                {
                    "type": "Control",
                    "scope": "#/properties/view/properties/subscribeToSelection",
                    "options": {
                        "format": "checkbox"
                    }
                }
            ]
        }
    ]
}